{
	"docID": "130276",
	"globalSID": "942266,942267,942268",
	"pronouns": [
		{
			"st": 105,
			"coref_index": 148,
			"id": 0,
			"en": 108,
			"ancestor": "1-0",
			"surface": "이 역"
		}
	],
	"parID": "2",
	"entities": [
		{
			"kbox_types": [
				"ArchitecturalStructure",
				"Place",
				"RailwayLine",
				"RouteOfTransportation",
				"Infrastructure"
			],
			"st": 3,
			"eType": "WIKILINK",
			"entityName": "한국고속철도",
			"id": 0,
			"ne_type": "LOCATION",
			"en": 6,
			"ancestor": "-1",
			"is_target": true,
			"surface": "KTX",
			"coref_index": 147
		},
		{
			"kbox_types": [
				"Train",
				"MeanOfTransportation"
			],
			"st": 8,
			"eType": "WIKILINK",
			"entityName": "ITX-새마을",
			"id": 1,
			"ne_type": "ETC",
			"en": 15,
			"ancestor": "-1",
			"is_target": true,
			"surface": "ITX-새마을",
			"coref_index": 151
		},
		{
			"kbox_types": [
				"NULL"
			],
			"st": 17,
			"eType": "WIKILINK",
			"entityName": "무궁화호",
			"id": 2,
			"ne_type": "ETC",
			"en": 21,
			"ancestor": "-1",
			"is_target": true,
			"surface": "무궁화호",
			"coref_index": 145
		},
		{
			"kbox_types": [
				"NULL"
			],
			"st": 23,
			"eType": "WIKILINK",
			"entityName": "남도해양열차",
			"id": 3,
			"ne_type": "ETC",
			"en": 29,
			"ancestor": "-1",
			"is_target": true,
			"surface": "남도해양열차",
			"coref_index": 146
		},
		{
			"kbox_types": [
				"ArchitecturalStructure",
				"Place",
				"RailwayLine",
				"RouteOfTransportation",
				"Infrastructure"
			],
			"st": 39,
			"eType": "WIKILINK",
			"entityName": "호남선",
			"id": 4,
			"ne_type": "LOCATION",
			"en": 42,
			"ancestor": "1-1",
			"is_target": true,
			"surface": "호남선",
			"coref_index": 144
		},
		{
			"kbox_types": [
				"ArchitecturalStructure",
				"Place",
				"RailwayLine",
				"RouteOfTransportation",
				"Infrastructure"
			],
			"st": 44,
			"eType": "WIKILINK",
			"entityName": "장항선",
			"id": 5,
			"ne_type": "LOCATION",
			"en": 47,
			"ancestor": "-1",
			"is_target": true,
			"surface": "장항선"
		},
		{
			"kbox_types": [
				"NULL"
			],
			"st": 48,
			"eType": "WIKILINK",
			"entityName": "무궁화호",
			"id": 6,
			"ne_type": "ETC",
			"en": 52,
			"ancestor": "2-2",
			"is_target": true,
			"surface": "무궁화호",
			"coref_index": 145
		},
		{
			"kbox_types": [
				"Year",
				"MusicalWork",
				"TimePeriod",
				"Work",
				"Album"
			],
			"st": 68,
			"eType": "WIKILINK",
			"entityName": "2013년",
			"id": 7,
			"ne_type": "TIME",
			"en": 73,
			"ancestor": "",
			"is_target": false,
			"surface": "2013년"
		},
		{
			"kbox_types": [
				"NULL"
			],
			"st": 74,
			"eType": "WIKILINK",
			"entityName": "12월_13일",
			"id": 8,
			"ne_type": "TIME",
			"en": 81,
			"ancestor": "",
			"is_target": false,
			"surface": "12월_13일"
		},
		{
			"kbox_types": [
				"ArchitecturalStructure",
				"Place",
				"Station",
				"Place",
				"Infrastructure",
				"RailwayStation"
			],
			"st": 84,
			"eType": "WIKILINK",
			"entityName": "광주송정역",
			"id": 9,
			"ne_type": "LOCATION",
			"en": 89,
			"ancestor": "-1",
			"is_target": true,
			"surface": "광주송정역"
		},
		{
			"kbox_types": [
				"NULL"
			],
			"st": 97,
			"eType": "WIKILINK",
			"entityName": "남도해양열차",
			"id": 10,
			"ne_type": "ETC",
			"en": 103,
			"ancestor": "2-3",
			"is_target": true,
			"surface": "남도해양열차",
			"coref_index": 146
		},
		{
			"kbox_types": [
				"ArchitecturalStructure",
				"Place",
				"RailwayLine",
				"RouteOfTransportation",
				"Infrastructure"
			],
			"st": 121,
			"eType": "WIKILINK",
			"entityName": "전라선",
			"id": 11,
			"ne_type": "LOCATION",
			"en": 124,
			"ancestor": "-1",
			"is_target": true,
			"surface": "전라선"
		},
		{
			"kbox_types": [
				"ArchitecturalStructure",
				"Place",
				"Station",
				"Infrastructure",
				"RailwayStation"
			],
			"st": 125,
			"eType": "WIKILINK",
			"entityName": "서울역",
			"id": 12,
			"ne_type": "LOCATION",
			"en": 128,
			"ancestor": "-1",
			"is_target": true,
			"surface": "서울역",
			"coref_index": 149
		},
		{
			"kbox_types": [
				"ArchitecturalStructure",
				"Place",
				"Station",
				"Place",
				"Infrastructure",
				"RailwayStation"
			],
			"st": 131,
			"eType": "WIKILINK",
			"entityName": "여수엑스포역",
			"id": 13,
			"ne_type": "LOCATION",
			"en": 137,
			"ancestor": "-1",
			"is_target": true,
			"surface": "여수엑스포역"
		},
		{
			"kbox_types": [
				"Year",
				"MusicalWork",
				"Album",
				"TimePeriod",
				"Work"
			],
			"st": 154,
			"eType": "WIKILINK",
			"entityName": "2015년",
			"id": 14,
			"ne_type": "TIME",
			"en": 159,
			"ancestor": "",
			"is_target": false,
			"surface": "2015년"
		},
		{
			"kbox_types": [
				"NULL"
			],
			"st": 160,
			"eType": "WIKILINK",
			"entityName": "4월_2일",
			"id": 15,
			"ne_type": "TIME",
			"en": 165,
			"ancestor": "",
			"is_target": false,
			"surface": "4월_2일"
		},
		{
			"kbox_types": [
				"ArchitecturalStructure",
				"Place",
				"RailwayLine",
				"RouteOfTransportation",
				"Infrastructure"
			],
			"st": 166,
			"eType": "WIKILINK",
			"entityName": "호남고속철도",
			"id": 16,
			"ne_type": "LOCATION",
			"en": 172,
			"ancestor": "-1",
			"is_target": true,
			"surface": "호남고속철도"
		},
		{
			"kbox_types": [
				"ArchitecturalStructure",
				"Place",
				"RailwayLine",
				"RouteOfTransportation",
				"Infrastructure"
			],
			"st": 179,
			"eType": "WIKILINK",
			"entityName": "한국고속철도",
			"id": 17,
			"ne_type": "LOCATION",
			"en": 182,
			"ancestor": "2-0",
			"is_target": true,
			"surface": "KTX",
			"coref_index": 147
		},
		{
			"kbox_types": [
				"NULL"
			],
			"st": 191,
			"eType": "WIKILINK",
			"entityName": "주말",
			"id": 18,
			"ne_type": "ETC",
			"en": 193,
			"ancestor": "-1",
			"is_target": true,
			"surface": "주말"
		},
		{
			"kbox_types": [
				"Year",
				"Agent",
				"Organisation",
				"TimePeriod",
				"Company"
			],
			"st": 212,
			"eType": "WIKILINK",
			"entityName": "2016년",
			"id": 19,
			"ne_type": "TIME",
			"en": 217,
			"ancestor": "",
			"is_target": false,
			"surface": "2016년"
		},
		{
			"kbox_types": [
				"NULL"
			],
			"st": 218,
			"eType": "WIKILINK",
			"entityName": "12월",
			"id": 20,
			"ne_type": "TIME",
			"en": 221,
			"ancestor": "",
			"is_target": false,
			"surface": "12월"
		},
		{
			"kbox_types": [
				"ArchitecturalStructure",
				"Place",
				"Station",
				"Place",
				"Infrastructure",
				"RailwayStation"
			],
			"st": 224,
			"eType": "ELU",
			"entityName": "서대전역",
			"id": 21,
			"ne_type": "LOCATION",
			"en": 228,
			"ancestor": "1-0",
			"is_target": true,
			"surface": "서대전역",
			"coref_index": 148
		},
		{
			"kbox_types": [
				"ArchitecturalStructure",
				"Place",
				"RailwayLine",
				"RouteOfTransportation",
				"Infrastructure"
			],
			"st": 235,
			"eType": "WIKILINK",
			"entityName": "한국고속철도",
			"id": 22,
			"ne_type": "LOCATION",
			"en": 238,
			"ancestor": "2-0",
			"is_target": true,
			"surface": "KTX",
			"coref_index": 147
		},
		{
			"kbox_types": [
				"ArchitecturalStructure",
				"Place",
				"Station",
				"Infrastructure",
				"RailwayStation"
			],
			"st": 245,
			"eType": "WIKILINK",
			"entityName": "서울역",
			"id": 23,
			"ne_type": "LOCATION",
			"en": 248,
			"ancestor": "2-12",
			"is_target": true,
			"surface": "서울역",
			"coref_index": 149
		},
		{
			"kbox_types": [
				"NULL"
			],
			"st": 54,
			"eType": "NEW",
			"entityName": "",
			"id": 24,
			"ne_type": "LOCATION",
			"en": 57,
			"ancestor": "1-0",
			"is_target": true,
			"surface": "이_역",
			"coref_index": 148
		}
	],
	"plainText": "현재 KTX, ITX-새마을, 무궁화호, 남도해양열차가 정차하며 일부 호남선, 장항선 무궁화호는 이_역에서 시·종착한다. 2013년 12월_13일부터 광주송정역에서 출발하는 남도해양열차도 이 역에서 시·종착하였으나, 전라선(서울역 - 여수엑스포역) 구간을 운행하며 정차한다. 2015년 4월_2일 호남고속철도 개통 이후 KTX는 1일 16회(주말 1일 18회) 정차하고 있었으나 2016년 12월부터 서대전역을 경유하는 KTX가 증편되고 서울역 또는 호남 방향으로의 운행을 재개하였다."
}