{
	"entities": [
		{
			"kbox_types": [
				"SoccerPlayer",
				"Athlete",
				"Agent",
				"Person"
			],
			"id": 0,
			"ne_type": "PERSON",
			"st": 0,
			"eType": "ELU",
			"entityName": "누리_샤힌",
			"en": 5,
			"is_target": true,
			"surface": "누리_샤힌",
			"coref_index": 184,
			"ancestor": "-1"
		},
		{
			"kbox_types": [
				"Region",
				"PopulatedPlace",
				"AdministrativeRegion",
				"Place",
				"Settlement",
				"AdministrativeRegion"
			],
			"id": 1,
			"ne_type": "LOCATION",
			"st": 22,
			"eType": "WIKILINK",
			"entityName": "노르트라인베스트팔렌_주",
			"en": 34,
			"is_target": true,
			"surface": "노르트라인베스트팔렌_주",
			"ancestor": "-1"
		},
		{
			"kbox_types": [
				"Town",
				"PopulatedPlace",
				"Settlement",
				"Town",
				"Place"
			],
			"id": 2,
			"ne_type": "LOCATION",
			"st": 35,
			"eType": "WIKILINK",
			"entityName": "뤼덴샤이트",
			"en": 40,
			"is_target": true,
			"surface": "뤼덴샤이트",
			"coref_index": 186,
			"ancestor": "-1"
		},
		{
			"kbox_types": [
				"Agent",
				"SportsLeague",
				"Organisation",
				"SoccerLeague"
			],
			"id": 3,
			"ne_type": "ORGANIZATION",
			"st": 61,
			"eType": "WIKILINK",
			"entityName": "푸스발-분데스리가",
			"en": 66,
			"is_target": true,
			"surface": "분데스리가",
			"ancestor": "-1"
		},
		{
			"kbox_types": [
				"SoccerClub",
				"Agent",
				"SportsTeam",
				"Organisation"
			],
			"id": 4,
			"ne_type": "ORGANIZATION",
			"st": 68,
			"eType": "WIKILINK",
			"entityName": "보루시아_도르트문트",
			"en": 73,
			"is_target": true,
			"surface": "도르트문트",
			"coref_index": 183,
			"ancestor": "-1"
		},
		{
			"kbox_types": [
				"SoccerClub",
				"Agent",
				"SportsTeam",
				"Organisation"
			],
			"id": 5,
			"ne_type": "ORGANIZATION",
			"st": 75,
			"eType": "WIKILINK",
			"entityName": "터키_축구_국가대표팀",
			"en": 83,
			"is_target": true,
			"surface": "터키_국가대표팀",
			"ancestor": "-1"
		},
		{
			"kbox_types": [
				"NULL"
			],
			"id": 6,
			"ne_type": "ETC",
			"st": 93,
			"eType": "WIKILINK",
			"entityName": "미드필더",
			"en": 100,
			"is_target": true,
			"surface": "중앙_미드필더",
			"ancestor": "-1"
		},
		{
			"kbox_types": [
				"NULL"
			],
			"id": 7,
			"ne_type": "TIME",
			"st": 9,
			"eType": "NEW",
			"entityName": "",
			"en": 20,
			"is_target": false,
			"surface": "1988년_9월_5일",
			"ancestor": ""
		},
		{
			"kbox_types": [
				"NULL"
			],
			"id": 8,
			"ne_type": "LOCATION",
			"st": 46,
			"eType": "NEW",
			"entityName": "",
			"en": 48,
			"is_target": true,
			"surface": "터키",
			"coref_index": 185,
			"ancestor": "-1"
		},
		{
			"kbox_types": [
				"PopulatedPlace",
				"Place",
				"Settlement",
				"PopulatedPlace",
				"City"
			],
			"id": 9,
			"ne_type": "LOCATION",
			"st": 130,
			"eType": "ELU",
			"entityName": "도르트문트",
			"en": 135,
			"is_target": true,
			"surface": "도르트문트",
			"coref_index": 183,
			"ancestor": "1-4"
		},
		{
			"kbox_types": [
				"FootballLeagueSeason",
				"SportsSeason",
				"SportsTeamSeason"
			],
			"id": 10,
			"ne_type": "ETC",
			"st": 151,
			"eType": "WIKILINK",
			"entityName": "푸스발-분데스리가_2010-11",
			"en": 161,
			"is_target": true,
			"surface": "2010-11_시즌",
			"ancestor": "-1"
		},
		{
			"kbox_types": [
				"SoccerClub",
				"Agent",
				"SportsTeam",
				"Organisation"
			],
			"id": 11,
			"ne_type": "ORGANIZATION",
			"st": 184,
			"eType": "WIKILINK",
			"entityName": "페예노르트",
			"en": 189,
			"is_target": true,
			"surface": "페예노르트",
			"coref_index": 187,
			"ancestor": "-1"
		},
		{
			"kbox_types": [
				"SoccerClub",
				"Agent",
				"SportsTeam",
				"Organisation"
			],
			"id": 12,
			"ne_type": "ORGANIZATION",
			"st": 225,
			"eType": "WIKILINK",
			"entityName": "레알_마드리드_CF",
			"en": 232,
			"is_target": true,
			"surface": "레알_마드리드",
			"ancestor": "-1"
		},
		{
			"kbox_types": [
				"SoccerClub",
				"Agent",
				"SportsTeam",
				"Organisation"
			],
			"id": 13,
			"ne_type": "ORGANIZATION",
			"st": 254,
			"eType": "WIKILINK",
			"entityName": "리버풀_FC",
			"en": 257,
			"is_target": true,
			"surface": "리버풀",
			"ancestor": "-1"
		},
		{
			"kbox_types": [
				"PopulatedPlace",
				"Place",
				"Settlement",
				"PopulatedPlace",
				"City"
			],
			"id": 14,
			"ne_type": "LOCATION",
			"st": 289,
			"eType": "ELU",
			"entityName": "도르트문트",
			"en": 294,
			"is_target": true,
			"surface": "도르트문트",
			"coref_index": 183,
			"ancestor": "1-9"
		},
		{
			"kbox_types": [
				"NULL"
			],
			"id": 15,
			"ne_type": "TIME",
			"st": 191,
			"eType": "NEW",
			"entityName": "",
			"en": 193,
			"is_target": false,
			"surface": "1년",
			"ancestor": ""
		},
		{
			"kbox_types": [
				"NULL"
			],
			"id": 16,
			"ne_type": "PERSON",
			"st": 250,
			"eType": "NEW",
			"entityName": "",
			"en": 252,
			"is_target": true,
			"surface": "샤힌",
			"coref_index": 184,
			"ancestor": "1-0"
		},
		{
			"kbox_types": [
				"NULL"
			],
			"id": 17,
			"ne_type": "TIME",
			"st": 272,
			"eType": "NEW",
			"entityName": "",
			"en": 280,
			"is_target": false,
			"surface": "2013년_1월",
			"ancestor": ""
		},
		{
			"kbox_types": [
				"NULL"
			],
			"id": 18,
			"ne_type": "ETC",
			"st": 356,
			"eType": "ELU",
			"entityName": "국가대표팀",
			"en": 361,
			"is_target": true,
			"surface": "국가대표팀",
			"ancestor": "-1"
		},
		{
			"kbox_types": [
				"SoccerTournament",
				"FootballMatch",
				"Tournament",
				"Event",
				"SocietalEvent",
				"SportsEvent"
			],
			"id": 19,
			"ne_type": "ETC",
			"st": 384,
			"eType": "WIKILINK",
			"entityName": "UEFA_유로_2016",
			"en": 396,
			"is_target": true,
			"surface": "UEFA_유로_2016",
			"ancestor": "-1"
		},
		{
			"kbox_types": [
				"NULL"
			],
			"id": 20,
			"ne_type": "ORGANIZATION",
			"st": 333,
			"eType": "NEW",
			"entityName": "",
			"en": 335,
			"is_target": true,
			"surface": "터키",
			"coref_index": 185,
			"ancestor": "1-8"
		},
		{
			"kbox_types": [
				"NULL"
			],
			"id": 21,
			"ne_type": "PERSON",
			"st": 315,
			"eType": "NEW",
			"entityName": "",
			"en": 317,
			"is_target": true,
			"surface": "샤힌",
			"coref_index": 184,
			"ancestor": "1-0"
		},
		{
			"kbox_types": [
				"NULL"
			],
			"id": 22,
			"ne_type": "ORGANIZATION",
			"st": 319,
			"eType": "NEW",
			"entityName": "",
			"en": 323,
			"is_target": true,
			"surface": "U-16",
			"ancestor": "-1"
		},
		{
			"kbox_types": [
				"NULL"
			],
			"id": 23,
			"ne_type": "ETC",
			"st": 412,
			"eType": "ELU",
			"en": 415,
			"entityName": "프라이버시",
			"is_target": true,
			"surface": "사생활",
			"ancestor": "-1"
		},
		{
			"kbox_types": [
				"Town",
				"PopulatedPlace",
				"Settlement",
				"Town",
				"Place"
			],
			"id": 24,
			"ne_type": "LOCATION",
			"st": 420,
			"eType": "WIKILINK",
			"en": 425,
			"entityName": "뤼덴샤이트",
			"is_target": true,
			"surface": "뤼덴샤이트",
			"coref_index": 186,
			"ancestor": "1-2"
		},
		{
			"kbox_types": [
				"EthnicGroup"
			],
			"id": 25,
			"ne_type": "ETC",
			"st": 431,
			"eType": "WIKILINK",
			"en": 434,
			"entityName": "터키인",
			"is_target": true,
			"surface": "터키계",
			"ancestor": "-1"
		},
		{
			"kbox_types": [
				"NULL"
			],
			"id": 26,
			"ne_type": "ETC",
			"st": 446,
			"eType": "WIKILINK",
			"en": 451,
			"entityName": "마이너차겐",
			"is_target": true,
			"surface": "마이너차겐",
			"ancestor": "-1"
		},
		{
			"kbox_types": [
				"Agent",
				"PopulatedPlace",
				"Place",
				"Settlement"
			],
			"id": 27,
			"ne_type": "LOCATION",
			"st": 525,
			"eType": "WIKILINK",
			"en": 529,
			"entityName": "마드리드",
			"is_target": true,
			"surface": "마드리드",
			"ancestor": "-1"
		},
		{
			"kbox_types": [
				"Language"
			],
			"id": 28,
			"ne_type": "ETC",
			"st": 542,
			"eType": "WIKILINK",
			"en": 545,
			"entityName": "터키어",
			"is_target": true,
			"surface": "터키어",
			"ancestor": "-1"
		},
		{
			"kbox_types": [
				"Language"
			],
			"id": 29,
			"ne_type": "ETC",
			"st": 547,
			"eType": "WIKILINK",
			"en": 550,
			"entityName": "독일어",
			"is_target": true,
			"surface": "독일어",
			"ancestor": "-1"
		},
		{
			"kbox_types": [
				"Language"
			],
			"id": 30,
			"ne_type": "ETC",
			"st": 552,
			"eType": "WIKILINK",
			"en": 554,
			"entityName": "영어",
			"is_target": true,
			"surface": "영어",
			"ancestor": "-1"
		},
		{
			"kbox_types": [
				"Language"
			],
			"id": 31,
			"ne_type": "ETC",
			"st": 556,
			"eType": "WIKILINK",
			"en": 561,
			"entityName": "네덜란드어",
			"is_target": true,
			"surface": "네덜란드어",
			"ancestor": "-1"
		},
		{
			"kbox_types": [
				"Language"
			],
			"id": 32,
			"ne_type": "ETC",
			"st": 567,
			"eType": "WIKILINK",
			"en": 571,
			"entityName": "스페인어",
			"is_target": true,
			"surface": "스페인어",
			"ancestor": "-1"
		},
		{
			"kbox_types": [
				"NULL"
			],
			"id": 33,
			"ne_type": "TIME",
			"st": 484,
			"eType": "NEW",
			"en": 493,
			"entityName": "",
			"is_target": false,
			"surface": "2007년_11월",
			"ancestor": ""
		},
		{
			"kbox_types": [
				"NULL"
			],
			"id": 34,
			"ne_type": "PERSON",
			"st": 472,
			"eType": "NEW",
			"en": 482,
			"entityName": "",
			"is_target": true,
			"surface": "투우바_에메니-샤힌",
			"ancestor": "-1"
		},
		{
			"kbox_types": [
				"NULL"
			],
			"id": 35,
			"ne_type": "TIME",
			"st": 501,
			"eType": "NEW",
			"en": 509,
			"entityName": "",
			"is_target": false,
			"surface": "2011년_9월",
			"ancestor": ""
		},
		{
			"kbox_types": [
				"SoccerClub",
				"Agent",
				"SportsTeam",
				"Organisation"
			],
			"id": 36,
			"ne_type": "ORGANIZATION",
			"st": 668,
			"eType": "WIKILINK",
			"en": 673,
			"entityName": "보루시아_도르트문트",
			"is_target": true,
			"surface": "도르트문트",
			"coref_index": 183,
			"ancestor": "1-4"
		},
		{
			"kbox_types": [
				"NULL"
			],
			"id": 37,
			"ne_type": "PERSON",
			"st": 605,
			"eType": "NEW",
			"en": 607,
			"entityName": "",
			"is_target": true,
			"surface": "샤힌",
			"coref_index": 184,
			"ancestor": "1-0"
		},
		{
			"kbox_types": [
				"NULL"
			],
			"id": 38,
			"ne_type": "TIME",
			"st": 655,
			"eType": "NEW",
			"en": 660,
			"entityName": "",
			"is_target": false,
			"surface": "2001년",
			"ancestor": ""
		},
		{
			"kbox_types": [
				"PopulatedPlace",
				"Place",
				"Settlement",
				"PopulatedPlace",
				"City"
			],
			"id": 39,
			"ne_type": "LOCATION",
			"st": 681,
			"eType": "ELU",
			"en": 686,
			"entityName": "도르트문트",
			"is_target": true,
			"surface": "도르트문트",
			"coref_index": 183,
			"ancestor": "1-9"
		},
		{
			"kbox_types": [
				"PopulatedPlace",
				"Place",
				"Settlement",
				"PopulatedPlace",
				"City"
			],
			"id": 40,
			"ne_type": "LOCATION",
			"st": 756,
			"eType": "ELU",
			"en": 761,
			"entityName": "도르트문트",
			"is_target": true,
			"surface": "도르트문트",
			"coref_index": 183,
			"ancestor": "1-9"
		},
		{
			"kbox_types": [
				"PopulatedPlace",
				"Settlement",
				"PopulatedPlace",
				"City",
				"Place"
			],
			"id": 41,
			"ne_type": "LOCATION",
			"st": 763,
			"eType": "ELU",
			"en": 768,
			"entityName": "뉘른베르크",
			"is_target": true,
			"surface": "뉘른베르크",
			"ancestor": "-1"
		},
		{
			"kbox_types": [
				"NULL"
			],
			"id": 42,
			"ne_type": "TIME",
			"st": 687,
			"eType": "NEW",
			"en": 698,
			"entityName": "",
			"is_target": false,
			"surface": "2005년_8월_6일",
			"ancestor": ""
		},
		{
			"kbox_types": [
				"NULL"
			],
			"id": 43,
			"ne_type": "TIME",
			"st": 746,
			"eType": "NEW",
			"en": 753,
			"entityName": "",
			"is_target": false,
			"surface": "11월_25일",
			"ancestor": ""
		},
		{
			"kbox_types": [
				"NULL"
			],
			"id": 44,
			"ne_type": "TIME",
			"st": 806,
			"eType": "NEW",
			"entityName": "",
			"en": 817,
			"is_target": false,
			"surface": "2007년_7월_5일",
			"ancestor": ""
		},
		{
			"kbox_types": [
				"NULL"
			],
			"id": 45,
			"ne_type": "PERSON",
			"st": 819,
			"eType": "NEW",
			"entityName": "",
			"en": 821,
			"is_target": true,
			"surface": "샤힌",
			"coref_index": 184,
			"ancestor": "1-0"
		},
		{
			"kbox_types": [
				"NULL"
			],
			"id": 46,
			"ne_type": "ORGANIZATION",
			"st": 823,
			"eType": "NEW",
			"entityName": "",
			"en": 835,
			"is_target": true,
			"surface": "에레디비시의_페예노르트",
			"coref_index": 187,
			"ancestor": "1-11"
		},
		{
			"kbox_types": [
				"NULL"
			],
			"id": 47,
			"ne_type": "PERSON",
			"st": 862,
			"eType": "NEW",
			"entityName": "",
			"en": 876,
			"is_target": true,
			"surface": "베르트_판_마르베이크_감독",
			"ancestor": "-1"
		},
		{
			"kbox_types": [
				"NULL"
			],
			"id": 48,
			"ne_type": "ETC",
			"st": 878,
			"eType": "NEW",
			"entityName": "",
			"en": 880,
			"is_target": true,
			"surface": "재회",
			"ancestor": "-1"
		}
	],
	"globalSID": "953532,953533,953534,953535,953536,953537,953538,953539,953540,953541,953542,953543,953544,953545,953546,953547,953548,953549,953550",
	"parID": "1",
	"pronouns": [
		{
			"id": 0,
			"ancestor": "1-0",
			"st": 90,
			"en": 91,
			"surface": "그",
			"coref_index": 184
		},
		{
			"id": 1,
			"ancestor": "1-0",
			"st": 127,
			"en": 128,
			"surface": "그",
			"coref_index": 184
		},
		{
			"id": 2,
			"ancestor": "1-0",
			"st": 208,
			"en": 209,
			"surface": "그",
			"coref_index": 184
		},
		{
			"id": 3,
			"ancestor": "1-21",
			"st": 343,
			"en": 344,
			"surface": "그",
			"coref_index": 184
		},
		{
			"id": 4,
			"en": 445,
			"ancestor": "-1",
			"st": 444,
			"surface": "나"
		},
		{
			"id": 5,
			"en": 453,
			"ancestor": "-1",
			"st": 444,
			"surface": "나 마이너차겐에서"
		},
		{
			"id": 6,
			"ancestor": "1-21",
			"st": 466,
			"en": 467,
			"surface": "그",
			"coref_index": 184
		},
		{
			"id": 7,
			"en": 745,
			"ancestor": "-1",
			"st": 741,
			"surface": "같은 해"
		},
		{
			"id": 8,
			"en": 755,
			"ancestor": "-1",
			"st": 741,
			"surface": "같은 해 11월_25일에는"
		},
		{
			"id": 9,
			"ancestor": "1-0",
			"st": 854,
			"en": 855,
			"surface": "그",
			"coref_index": 184
		},
		{
			"id": 10,
			"en": 877,
			"surface": "그를 지도했던 베르트_판_마르베이크_감독과",
			"st": 854,
			"ancestor": "-1"
		}
	],
	"plainText": "누리_샤힌 (, 1988년_9월_5일, 노르트라인베스트팔렌_주 뤼덴샤이트 ~) 은 터키의 축구 선수로, 현재 분데스리가의 도르트문트와 터키_국가대표팀 소속이다. 그는 중앙_미드필더로 주로 활약하며, 패스 능력으로 알려져 있다. 그는 도르트문트에서 데뷔해 6년을 보냈고, 2010-11_시즌에 분데스리가 우승도 거두었는데, 막간에 페예노르트로 1년 임대되기도 했다. 이후, 그는 2011년에 €10M으로 레알_마드리드에 입단했다. 2012년 8월, 샤힌은 리버풀 1년 임대에 합의했지만, 2013년_1월에 파기되었고, 도르트문트에 18개월 임대로 복귀하게 되었다. 샤힌은 U-16 대표팀 시절부터 터키를 대표했다. 그는 2005년에 성인 국가대표팀에 데뷔해 45번 국제 경기에 출전했고, UEFA_유로_2016에 자국을 대표로 나갔었다. 사생활 샤힌은 뤼덴샤이트 출신으로 터키계 부모님 사이에서 나 마이너차겐에서 유년 시절을 보냈다. 그는 사촌 투우바_에메니-샤힌과 2007년_11월에 결혼했다. 2011년_9월, 둘 사이에 아들 외메르가 마드리드에서 출생했다. 샤힌은 터키어, 독일어, 영어, 네덜란드어, 그리고 스페인어의 5개국어를 유창히 구사할 수 있다. 클럽 경력 초기 경력 샤힌은 6세에 마이너차겐에 입단하면서 축구를 시작했다. 마이너차겐에서 7년을 보낸 샤힌은 2001년에 프로 구단 도르트문트에 입단했다. 도르트문트 2005년_8월_6일, 16세 334세의 나이로, 샤힌은 분데스리가 최연소 출장 기록을 세웠고, 같은 해 11월_25일에는 도르트문트와 뉘른베르크 간 경기에서 골을 넣어 분데스리가 최연소 득점 기록도 갈아치웠다. 2007년_7월_5일, 샤힌은 에레디비시의_페예노르트로 1년 임대되어 도르트문트 시절 그를 지도했던 베르트_판_마르베이크_감독과 재회했다. ",
	"docID": "132777"
}